rslearn/__init__.py
rslearn/__version__.py
rslearn/_typing.py
rslearn/example.py
rslearn/preprocessing.py
rslearn/rsimage.py
rslearn/utils.py
rslearn/wraper/_base.py
rslearn/wraper/classfier.py
rslearn/wraper/cluster.py
remotesense_learn-0.0.4.dist-info/LICENSE
remotesense_learn-0.0.4.dist-info/METADATA
remotesense_learn-0.0.4.dist-info/WHEEL
remotesense_learn-0.0.4.dist-info/top_level.txt
remotesense_learn-0.0.4.dist-info/RECORD
