Metadata-Version: 2.1
Name: remotesense-learn
Version: 0.0.4
Summary: A toolkit for remote sensing machine learning classification based on scikit-learn 
Author-email: Wang Wenqi <wangwenqi23@mails.ucas.ac.cn>
Project-URL: Homepage, https://github.com/pypa/sampleproject
Project-URL: Bug Tracker, https://github.com/pypa/sampleproject/issues
Classifier: Programming Language :: Python :: 3
Classifier: License :: OSI Approved :: Mulan Permissive Software License v2 (MulanPSL-2.0)
Classifier: Operating System :: OS Independent
Requires-Python: >=3.7
License-File: LICENSE
